fbnconfig/__init__.py
fbnconfig/access.py
fbnconfig/backoff_handler.py
fbnconfig/cleardown_module.py
fbnconfig/compliance.py
fbnconfig/configuration.py
fbnconfig/coretypes.py
fbnconfig/corporate_action.py
fbnconfig/custodian_accounts.py
fbnconfig/custom_data_model.py
fbnconfig/customentity.py
fbnconfig/cutlabel.py
fbnconfig/datatype.py
fbnconfig/deploy.py
fbnconfig/drive.py
fbnconfig/exceptions.py
fbnconfig/fund_accounting.py
fbnconfig/fund_configurations.py
fbnconfig/general_ledger_profile.py
fbnconfig/horizon.py
fbnconfig/http_client.py
fbnconfig/identifier_definition.py
fbnconfig/identity.py
fbnconfig/instrument_events.py
fbnconfig/load_module.py
fbnconfig/log.py
fbnconfig/lumi.py
fbnconfig/main.py
fbnconfig/notifications.py
fbnconfig/posting_module.py
fbnconfig/properties.py
fbnconfig/property.py
fbnconfig/recipe.py
fbnconfig/reference_list.py
fbnconfig/resource_abc.py
fbnconfig/scheduler.py
fbnconfig/schemagen.py
fbnconfig/sequence.py
fbnconfig/side_definition.py
fbnconfig/transaction_type.py
fbnconfig/urlfmt.py
fbnconfig/workflows.py
fbnconfig/workspace.py
fbnconfig-0.1.197.dist-info/METADATA
fbnconfig-0.1.197.dist-info/WHEEL
fbnconfig-0.1.197.dist-info/entry_points.txt
fbnconfig-0.1.197.dist-info/RECORD
