Metadata-Version: 2.4
Name: fbnconfig
Version: 0.1.197
Summary: fbnconfig is a python library (and commandline tool) to allow a declarative description of a LUSID environment
Author-email: FINBOURNE Technology <engineering@finbourne.com>
Requires-Python: ~=3.11
Requires-Dist: click<9,>=8.1.7
Requires-Dist: httpcore==1.0.9
Requires-Dist: httpx==0.28.1
Requires-Dist: jsonschema>=4.25.1
Requires-Dist: pydantic<=2.8.2,>=2.6.0
Requires-Dist: starlette>=0.48.0
Requires-Dist: uvicorn>=0.37.0
